mynameisdusit
